MANIFEST.in
manage.py
settings.py.sample
setup.py
django_teagarden.egg-info/PKG-INFO
django_teagarden.egg-info/SOURCES.txt
django_teagarden.egg-info/dependency_links.txt
django_teagarden.egg-info/requires.txt
django_teagarden.egg-info/top_level.txt
teagarden/__init__.py
teagarden/admin.py
teagarden/admin_views.py
teagarden/context_processors.py
teagarden/decorators.py
teagarden/filter.py
teagarden/library.py
teagarden/managers.py
teagarden/middleware.py
teagarden/models.py
teagarden/tests.py
teagarden/urls.py
teagarden/views.py
teagarden/fixtures/initial_data.json
teagarden/locale/de/LC_MESSAGES/django.po
teagarden/locale/en/LC_MESSAGES/django.po
teagarden/static/css/admin.css
teagarden/static/css/teagarden.css
teagarden/static/img/cross.png
teagarden/static/img/favicon.png
teagarden/static/img/icons.png
teagarden/static/img/logo.png
teagarden/static/img/tick.png
teagarden/static/js/script.js
teagarden/templates/base.html
teagarden/templates/dashboard.html
teagarden/templates/dashboard_sidebar.html
teagarden/templates/field_heading.html
teagarden/templates/field_row.html
teagarden/templates/field_star.html
teagarden/templates/footer.html
teagarden/templates/inbox.html
teagarden/templates/minimal.html
teagarden/templates/project.html
teagarden/templates/project_heading.html
teagarden/templates/project_row.html
teagarden/templates/projects.html
teagarden/templates/reference_heading.html
teagarden/templates/reference_row.html
teagarden/templates/settings.html
teagarden/templates/starred_field_heading.html
teagarden/templates/starred_field_row.html
teagarden/templates/starred_objects.html
teagarden/templates/starred_table_heading.html
teagarden/templates/starred_table_row.html
teagarden/templates/table.html
teagarden/templates/table_heading.html
teagarden/templates/table_row.html
teagarden/templates/table_star.html
teagarden/templates/user.html
teagarden/templates/user_popup.html
teagarden/templates/validation_error.html
teagarden/templates/admin/base.html
teagarden/templates/admin/base_site.html
teagarden/templates/registration/logged_out.html
teagarden/templates/registration/login.html
teagarden/templates/registration/password_reset_complete.html
