Metadata-Version: 1.0
Name: django-teagarden
Version: 0.0.1
Summary: Database planning, visualization and code generation
Home-page: http://django-teagarden.googlecode.com
Author: Henning Kage
Author-email: henning.kage@googlemail.com
License: GPL3
Platform: UNKNOWN
Classifier: Development Status :: 2 - Pre-Alpha
Classifier: Framework :: Django
Classifier: Intended Audience :: Developers
Classifier: License :: OSI Approved :: GNU General Public License (GPL)
Classifier: Natural Language :: English
Classifier: Operating System :: OS Independent
Classifier: Programming Language :: Python
